[{"Code":"BOL","Value":271.7944,"Year":1451606400000,"Type":"Other Milds"},{"Code":"BDI","Value":null,"Year":1451606400000,"Type":"Other Milds"},{"Code":"CMR","Value":null,"Year":1451606400000,"Type":"Other Milds"},{"Code":"CRI","Value":129.1077,"Year":1451606400000,"Type":"Other Milds"},{"Code":"CUB","Value":235.7138,"Year":1451606400000,"Type":"Other Milds"},{"Code":"COD","Value":null,"Year":1451606400000,"Type":"Other Milds"},{"Code":"DOM","Value":177.1862,"Year":1451606400000,"Type":"Other Milds"},{"Code":"ECU","Value":null,"Year":1451606400000,"Type":"Other Milds"},{"Code":"SLV","Value":89.5328,"Year":1451606400000,"Type":"Other Milds"},{"Code":"GTM","Value":135.4671,"Year":1451606400000,"Type":"Other Milds"},{"Code":"HTI","Value":null,"Year":1451606400000,"Type":"Other Milds"},{"Code":"HND","Value":93.1681,"Year":1451606400000,"Type":"Other Milds"},{"Code":"IND","Value":132.2063,"Year":1451606400000,"Type":"Other Milds"},{"Code":"JAM","Value":null,"Year":1451606400000,"Type":"Other Milds"},{"Code":"MDG","Value":null,"Year":1451606400000,"Type":"Other Milds"},{"Code":"MWI","Value":null,"Year":1451606400000,"Type":"Other Milds"},{"Code":"MEX","Value":null,"Year":1451606400000,"Type":"Other Milds"},{"Code":"NIC","Value":null,"Year":1451606400000,"Type":"Other Milds"},{"Code":"PAN","Value":null,"Year":1451606400000,"Type":"Other Milds"},{"Code":"PNG","Value":57.5014,"Year":1451606400000,"Type":"Other Milds"},{"Code":"PER","Value":78.8416,"Year":1451606400000,"Type":"Other Milds"},{"Code":"RWA","Value":null,"Year":1451606400000,"Type":"Other Milds"},{"Code":"LKA","Value":null,"Year":1451606400000,"Type":"Other Milds"},{"Code":"UGA","Value":71.0947,"Year":1451606400000,"Type":"Other Milds"},{"Code":"ZMB","Value":null,"Year":1451606400000,"Type":"Other Milds"}]