[{"Code": "AGO", "Value": null, "Year": 631152000000, "Type": "Brazilian Naturals"}, {"Code": "BRA", "Value": 54.3248, "Year": 631152000000, "Type": "Brazilian Naturals"}, {"Code": "ETH", "Value": 61.09, "Year": 631152000000, "Type": "Brazilian Naturals"}, {"Code": "IDN", "Value": null, "Year": 631152000000, "Type": "Brazilian Naturals"}, {"Code": "PHL", "Value": null, "Year": 631152000000, "Type": "Brazilian Naturals"}, {"Code": "THA", "Value": null, "Year": 631152000000, "Type": "Brazilian Naturals"}, {"Code": "VNM", "Value": null, "Year": 631152000000, "Type": "Brazilian Naturals"}, {"Code": "AGO", "Value": null, "Year": 662688000000, "Type": "Brazilian Naturals"}, {"Code": "BRA", "Value": 43.9931, "Year": 662688000000, "Type": "Brazilian Naturals"}, {"Code": "ETH", "Value": 68.1911, "Year": 662688000000, "Type": "Brazilian Naturals"}, {"Code": "IDN", "Value": null, "Year": 662688000000, "Type": "Brazilian Naturals"}, {"Code": "PHL", "Value": null, "Year": 662688000000, "Type": "Brazilian Naturals"}, {"Code": "THA", "Value": null, "Year": 662688000000, "Type": "Brazilian Naturals"}, {"Code": "VNM", "Value": null, "Year": 662688000000, "Type": "Brazilian Naturals"}, {"Code": "AGO", "Value": null, "Year": 694224000000, "Type": "Brazilian Naturals"}, {"Code": "BRA", "Value": 45.1989, "Year": 694224000000, "Type": "Brazilian Naturals"}, {"Code": "ETH", "Value": 61.2061, "Year": 694224000000, "Type": "Brazilian Naturals"}, {"Code": "IDN", "Value": null, "Year": 694224000000, "Type": "Brazilian Naturals"}, {"Code": "PHL", "Value": 55.7355, "Year": 694224000000, "Type": "Brazilian Naturals"}, {"Code": "THA", "Value": null, "Year": 694224000000, "Type": "Brazilian Naturals"}, {"Code": "VNM", "Value": null, "Year": 694224000000, "Type": "Brazilian Naturals"}, {"Code": "AGO", "Value": null, "Year": 725846400000, "Type": "Brazilian Naturals"}, {"Code": "BRA", "Value": 52.877, "Year": 725846400000, "Type": "Brazilian Naturals"}, {"Code": "ETH", "Value": 61.7186, "Year": 725846400000, "Type": "Brazilian Naturals"}, {"Code": "IDN", "Value": 115.5349, "Year": 725846400000, "Type": "Brazilian Naturals"}, {"Code": "PHL", "Value": 54.1985, "Year": 725846400000, "Type": "Brazilian Naturals"}, {"Code": "THA", "Value": null, "Year": 725846400000, "Type": "Brazilian Naturals"}, {"Code": "VNM", "Value": null, "Year": 725846400000, "Type": "Brazilian Naturals"}, {"Code": "AGO", "Value": null, "Year": 757382400000, "Type": "Brazilian Naturals"}, {"Code": "BRA", "Value": 114.5687, "Year": 757382400000, "Type": "Brazilian Naturals"}, {"Code": "ETH", "Value": 109.546, "Year": 757382400000, "Type": "Brazilian Naturals"}, {"Code": "IDN", "Value": 173.5073, "Year": 757382400000, "Type": "Brazilian Naturals"}, {"Code": "PHL", "Value": 99.6167, "Year": 757382400000, "Type": "Brazilian Naturals"}, {"Code": "THA", "Value": null, "Year": 757382400000, "Type": "Brazilian Naturals"}, {"Code": "VNM", "Value": null, "Year": 757382400000, "Type": "Brazilian Naturals"}, {"Code": "AGO", "Value": null, "Year": 788918400000, "Type": "Brazilian Naturals"}, {"Code": "BRA", "Value": 115.5228, "Year": 788918400000, "Type": "Brazilian Naturals"}, {"Code": "ETH", "Value": 115.0172, "Year": 788918400000, "Type": "Brazilian Naturals"}, {"Code": "IDN", "Value": null, "Year": 788918400000, "Type": "Brazilian Naturals"}, {"Code": "PHL", "Value": 106.301, "Year": 788918400000, "Type": "Brazilian Naturals"}, {"Code": "THA", "Value": null, "Year": 788918400000, "Type": "Brazilian Naturals"}, {"Code": "VNM", "Value": null, "Year": 788918400000, "Type": "Brazilian Naturals"}, {"Code": "AGO", "Value": null, "Year": 820454400000, "Type": "Brazilian Naturals"}, {"Code": "BRA", "Value": 96.3456, "Year": 820454400000, "Type": "Brazilian Naturals"}, {"Code": "ETH", "Value": 67.7365, "Year": 820454400000, "Type": "Brazilian Naturals"}, {"Code": "IDN", "Value": null, "Year": 820454400000, "Type": "Brazilian Naturals"}, {"Code": "PHL", "Value": 76.3125, "Year": 820454400000, "Type": "Brazilian Naturals"}, {"Code": "THA", "Value": null, "Year": 820454400000, "Type": "Brazilian Naturals"}, {"Code": "VNM", "Value": null, "Year": 820454400000, "Type": "Brazilian Naturals"}, {"Code": "AGO", "Value": null, "Year": 852076800000, "Type": "Brazilian Naturals"}, {"Code": "BRA", "Value": 145.4095, "Year": 852076800000, "Type": "Brazilian Naturals"}, {"Code": "ETH", "Value": 91.0557, "Year": 852076800000, "Type": "Brazilian Naturals"}, {"Code": "IDN", "Value": 112.2585, "Year": 852076800000, "Type": "Brazilian Naturals"}, {"Code": "PHL", "Value": 79.7375, "Year": 852076800000, "Type": "Brazilian Naturals"}, {"Code": "THA", "Value": null, "Year": 852076800000, "Type": "Brazilian Naturals"}, {"Code": "VNM", "Value": null, "Year": 852076800000, "Type": "Brazilian Naturals"}, {"Code": "AGO", "Value": null, "Year": 883612800000, "Type": "Brazilian Naturals"}, {"Code": "BRA", "Value": 105.2491, "Year": 883612800000, "Type": "Brazilian Naturals"}, {"Code": "ETH", "Value": 91.8639, "Year": 883612800000, "Type": "Brazilian Naturals"}, {"Code": "IDN", "Value": 99.4085, "Year": 883612800000, "Type": "Brazilian Naturals"}, {"Code": "PHL", "Value": 81.8728, "Year": 883612800000, "Type": "Brazilian Naturals"}, {"Code": "THA", "Value": null, "Year": 883612800000, "Type": "Brazilian Naturals"}, {"Code": "VNM", "Value": null, "Year": 883612800000, "Type": "Brazilian Naturals"}, {"Code": "AGO", "Value": null, "Year": 915148800000, "Type": "Brazilian Naturals"}, {"Code": "BRA", "Value": 74.0666, "Year": 915148800000, "Type": "Brazilian Naturals"}, {"Code": "ETH", "Value": 65.6448, "Year": 915148800000, "Type": "Brazilian Naturals"}, {"Code": "IDN", "Value": null, "Year": 915148800000, "Type": "Brazilian Naturals"}, {"Code": "PHL", "Value": 64.8877, "Year": 915148800000, "Type": "Brazilian Naturals"}, {"Code": "THA", "Value": null, "Year": 915148800000, "Type": "Brazilian Naturals"}, {"Code": "VNM", "Value": null, "Year": 915148800000, "Type": "Brazilian Naturals"}, {"Code": "AGO", "Value": null, "Year": 946684800000, "Type": "Brazilian Naturals"}, {"Code": "BRA", "Value": 65.9769, "Year": 946684800000, "Type": "Brazilian Naturals"}, {"Code": "ETH", "Value": 56.421, "Year": 946684800000, "Type": "Brazilian Naturals"}, {"Code": "IDN", "Value": 68.4091, "Year": 946684800000, "Type": "Brazilian Naturals"}, {"Code": "PHL", "Value": 37.044, "Year": 946684800000, "Type": "Brazilian Naturals"}, {"Code": "THA", "Value": null, "Year": 946684800000, "Type": "Brazilian Naturals"}, {"Code": "VNM", "Value": null, "Year": 946684800000, "Type": "Brazilian Naturals"}, {"Code": "AGO", "Value": null, "Year": 978307200000, "Type": "Brazilian Naturals"}, {"Code": "BRA", "Value": 37.0458, "Year": 978307200000, "Type": "Brazilian Naturals"}, {"Code": "ETH", "Value": 43.7795, "Year": 978307200000, "Type": "Brazilian Naturals"}, {"Code": "IDN", "Value": 53.6054, "Year": 978307200000, "Type": "Brazilian Naturals"}, {"Code": "PHL", "Value": 49.3555, "Year": 978307200000, "Type": "Brazilian Naturals"}, {"Code": "THA", "Value": null, "Year": 978307200000, "Type": "Brazilian Naturals"}, {"Code": "VNM", "Value": null, "Year": 978307200000, "Type": "Brazilian Naturals"}, {"Code": "AGO", "Value": null, "Year": 1009843200000, "Type": "Brazilian Naturals"}, {"Code": "BRA", "Value": 30.9089, "Year": 1009843200000, "Type": "Brazilian Naturals"}, {"Code": "ETH", "Value": 26.8781, "Year": 1009843200000, "Type": "Brazilian Naturals"}, {"Code": "IDN", "Value": 59.6569, "Year": 1009843200000, "Type": "Brazilian Naturals"}, {"Code": "PHL", "Value": 21.738, "Year": 1009843200000, "Type": "Brazilian Naturals"}, {"Code": "THA", "Value": null, "Year": 1009843200000, "Type": "Brazilian Naturals"}, {"Code": "VNM", "Value": null, "Year": 1009843200000, "Type": "Brazilian Naturals"}, {"Code": "AGO", "Value": null, "Year": 1041379200000, "Type": "Brazilian Naturals"}, {"Code": "BRA", "Value": 42.8184, "Year": 1041379200000, "Type": "Brazilian Naturals"}, {"Code": "ETH", "Value": 34.5679, "Year": 1041379200000, "Type": "Brazilian Naturals"}, {"Code": "IDN", "Value": 42.0479, "Year": 1041379200000, "Type": "Brazilian Naturals"}, {"Code": "PHL", "Value": 60.6343, "Year": 1041379200000, "Type": "Brazilian Naturals"}, {"Code": "THA", "Value": null, "Year": 1041379200000, "Type": "Brazilian Naturals"}, {"Code": "VNM", "Value": null, "Year": 1041379200000, "Type": "Brazilian Naturals"}, {"Code": "AGO", "Value": null, "Year": 1072915200000, "Type": "Brazilian Naturals"}, {"Code": "BRA", "Value": 56.3302, "Year": 1072915200000, "Type": "Brazilian Naturals"}, {"Code": "ETH", "Value": 48.8512, "Year": 1072915200000, "Type": "Brazilian Naturals"}, {"Code": "IDN", "Value": 80.6176, "Year": 1072915200000, "Type": "Brazilian Naturals"}, {"Code": "PHL", "Value": 66.2305, "Year": 1072915200000, "Type": "Brazilian Naturals"}, {"Code": "THA", "Value": null, "Year": 1072915200000, "Type": "Brazilian Naturals"}, {"Code": "VNM", "Value": null, "Year": 1072915200000, "Type": "Brazilian Naturals"}, {"Code": "AGO", "Value": null, "Year": 1104537600000, "Type": "Brazilian Naturals"}, {"Code": "BRA", "Value": 87.09, "Year": 1104537600000, "Type": "Brazilian Naturals"}, {"Code": "ETH", "Value": 64.2276, "Year": 1104537600000, "Type": "Brazilian Naturals"}, {"Code": "IDN", "Value": 117.0379, "Year": 1104537600000, "Type": "Brazilian Naturals"}, {"Code": "PHL", "Value": 79.9997, "Year": 1104537600000, "Type": "Brazilian Naturals"}, {"Code": "THA", "Value": null, "Year": 1104537600000, "Type": "Brazilian Naturals"}, {"Code": "VNM", "Value": null, "Year": 1104537600000, "Type": "Brazilian Naturals"}, {"Code": "AGO", "Value": null, "Year": 1136073600000, "Type": "Brazilian Naturals"}, {"Code": "BRA", "Value": 87.0178, "Year": 1136073600000, "Type": "Brazilian Naturals"}, {"Code": "ETH", "Value": 58.3172, "Year": 1136073600000, "Type": "Brazilian Naturals"}, {"Code": "IDN", "Value": 107.5163, "Year": 1136073600000, "Type": "Brazilian Naturals"}, {"Code": "PHL", "Value": 61.5072, "Year": 1136073600000, "Type": "Brazilian Naturals"}, {"Code": "THA", "Value": null, "Year": 1136073600000, "Type": "Brazilian Naturals"}, {"Code": "VNM", "Value": null, "Year": 1136073600000, "Type": "Brazilian Naturals"}, {"Code": "AGO", "Value": null, "Year": 1167609600000, "Type": "Brazilian Naturals"}, {"Code": "BRA", "Value": 98.2955, "Year": 1167609600000, "Type": "Brazilian Naturals"}, {"Code": "ETH", "Value": 69.829, "Year": 1167609600000, "Type": "Brazilian Naturals"}, {"Code": "IDN", "Value": 117.9882, "Year": 1167609600000, "Type": "Brazilian Naturals"}, {"Code": "PHL", "Value": 81.3725, "Year": 1167609600000, "Type": "Brazilian Naturals"}, {"Code": "THA", "Value": null, "Year": 1167609600000, "Type": "Brazilian Naturals"}, {"Code": "VNM", "Value": null, "Year": 1167609600000, "Type": "Brazilian Naturals"}, {"Code": "AGO", "Value": null, "Year": 1199145600000, "Type": "Brazilian Naturals"}, {"Code": "BRA", "Value": 109.2581, "Year": 1199145600000, "Type": "Brazilian Naturals"}, {"Code": "ETH", "Value": 71.7101, "Year": 1199145600000, "Type": "Brazilian Naturals"}, {"Code": "IDN", "Value": null, "Year": 1199145600000, "Type": "Brazilian Naturals"}, {"Code": "PHL", "Value": 95.5242, "Year": 1199145600000, "Type": "Brazilian Naturals"}, {"Code": "THA", "Value": null, "Year": 1199145600000, "Type": "Brazilian Naturals"}, {"Code": "VNM", "Value": null, "Year": 1199145600000, "Type": "Brazilian Naturals"}, {"Code": "AGO", "Value": null, "Year": 1230768000000, "Type": "Brazilian Naturals"}, {"Code": "BRA", "Value": 100.7993, "Year": 1230768000000, "Type": "Brazilian Naturals"}, {"Code": "ETH", "Value": 77.0621, "Year": 1230768000000, "Type": "Brazilian Naturals"}, {"Code": "IDN", "Value": null, "Year": 1230768000000, "Type": "Brazilian Naturals"}, {"Code": "PHL", "Value": null, "Year": 1230768000000, "Type": "Brazilian Naturals"}, {"Code": "THA", "Value": null, "Year": 1230768000000, "Type": "Brazilian Naturals"}, {"Code": "VNM", "Value": null, "Year": 1230768000000, "Type": "Brazilian Naturals"}, {"Code": "AGO", "Value": null, "Year": 1262304000000, "Type": "Brazilian Naturals"}, {"Code": "BRA", "Value": 133.9954, "Year": 1262304000000, "Type": "Brazilian Naturals"}, {"Code": "ETH", "Value": 85.4598, "Year": 1262304000000, "Type": "Brazilian Naturals"}, {"Code": "IDN", "Value": null, "Year": 1262304000000, "Type": "Brazilian Naturals"}, {"Code": "PHL", "Value": null, "Year": 1262304000000, "Type": "Brazilian Naturals"}, {"Code": "THA", "Value": null, "Year": 1262304000000, "Type": "Brazilian Naturals"}, {"Code": "VNM", "Value": null, "Year": 1262304000000, "Type": "Brazilian Naturals"}, {"Code": "AGO", "Value": null, "Year": 1293840000000, "Type": "Brazilian Naturals"}, {"Code": "BRA", "Value": 224.26, "Year": 1293840000000, "Type": "Brazilian Naturals"}, {"Code": "ETH", "Value": 145.4623, "Year": 1293840000000, "Type": "Brazilian Naturals"}, {"Code": "IDN", "Value": null, "Year": 1293840000000, "Type": "Brazilian Naturals"}, {"Code": "PHL", "Value": null, "Year": 1293840000000, "Type": "Brazilian Naturals"}, {"Code": "THA", "Value": null, "Year": 1293840000000, "Type": "Brazilian Naturals"}, {"Code": "VNM", "Value": null, "Year": 1293840000000, "Type": "Brazilian Naturals"}, {"Code": "AGO", "Value": 57.0161, "Year": 1325376000000, "Type": "Brazilian Naturals"}, {"Code": "BRA", "Value": 152.2879, "Year": 1325376000000, "Type": "Brazilian Naturals"}, {"Code": "ETH", "Value": 102.7897, "Year": 1325376000000, "Type": "Brazilian Naturals"}, {"Code": "IDN", "Value": null, "Year": 1325376000000, "Type": "Brazilian Naturals"}, {"Code": "PHL", "Value": 262.0105, "Year": 1325376000000, "Type": "Brazilian Naturals"}, {"Code": "THA", "Value": null, "Year": 1325376000000, "Type": "Brazilian Naturals"}, {"Code": "VNM", "Value": 84.4656, "Year": 1325376000000, "Type": "Brazilian Naturals"}, {"Code": "AGO", "Value": 37.6447, "Year": 1356998400000, "Type": "Brazilian Naturals"}, {"Code": "BRA", "Value": 102.1379, "Year": 1356998400000, "Type": "Brazilian Naturals"}, {"Code": "ETH", "Value": 73.3004, "Year": 1356998400000, "Type": "Brazilian Naturals"}, {"Code": "IDN", "Value": null, "Year": 1356998400000, "Type": "Brazilian Naturals"}, {"Code": "PHL", "Value": null, "Year": 1356998400000, "Type": "Brazilian Naturals"}, {"Code": "THA", "Value": 203.4373, "Year": 1356998400000, "Type": "Brazilian Naturals"}, {"Code": "VNM", "Value": null, "Year": 1356998400000, "Type": "Brazilian Naturals"}, {"Code": "AGO", "Value": 54.6078, "Year": 1388534400000, "Type": "Brazilian Naturals"}, {"Code": "BRA", "Value": 134.6969, "Year": 1388534400000, "Type": "Brazilian Naturals"}, {"Code": "ETH", "Value": 83.2356, "Year": 1388534400000, "Type": "Brazilian Naturals"}, {"Code": "IDN", "Value": null, "Year": 1388534400000, "Type": "Brazilian Naturals"}, {"Code": "PHL", "Value": null, "Year": 1388534400000, "Type": "Brazilian Naturals"}, {"Code": "THA", "Value": 113.3269, "Year": 1388534400000, "Type": "Brazilian Naturals"}, {"Code": "VNM", "Value": null, "Year": 1388534400000, "Type": "Brazilian Naturals"}, {"Code": "AGO", "Value": 45.812, "Year": 1420070400000, "Type": "Brazilian Naturals"}, {"Code": "BRA", "Value": 104.4866, "Year": 1420070400000, "Type": "Brazilian Naturals"}, {"Code": "ETH", "Value": 76.0297, "Year": 1420070400000, "Type": "Brazilian Naturals"}, {"Code": "IDN", "Value": null, "Year": 1420070400000, "Type": "Brazilian Naturals"}, {"Code": "PHL", "Value": null, "Year": 1420070400000, "Type": "Brazilian Naturals"}, {"Code": "THA", "Value": 124.5841, "Year": 1420070400000, "Type": "Brazilian Naturals"}, {"Code": "VNM", "Value": null, "Year": 1420070400000, "Type": "Brazilian Naturals"}, {"Code": "AGO", "Value": 100.4557, "Year": 1451606400000, "Type": "Brazilian Naturals"}, {"Code": "BRA", "Value": 107.8306, "Year": 1451606400000, "Type": "Brazilian Naturals"}, {"Code": "ETH", "Value": 87.3074, "Year": 1451606400000, "Type": "Brazilian Naturals"}, {"Code": "IDN", "Value": null, "Year": 1451606400000, "Type": "Brazilian Naturals"}, {"Code": "PHL", "Value": null, "Year": 1451606400000, "Type": "Brazilian Naturals"}, {"Code": "THA", "Value": null, "Year": 1451606400000, "Type": "Brazilian Naturals"}, {"Code": "VNM", "Value": null, "Year": 1451606400000, "Type": "Brazilian Naturals"}, {"Code": "AGO", "Value": 159.4754, "Year": 1483228800000, "Type": "Brazilian Naturals"}, {"Code": "BRA", "Value": 110.4757, "Year": 1483228800000, "Type": "Brazilian Naturals"}, {"Code": "ETH", "Value": 81.5073, "Year": 1483228800000, "Type": "Brazilian Naturals"}, {"Code": "IDN", "Value": null, "Year": 1483228800000, "Type": "Brazilian Naturals"}, {"Code": "PHL", "Value": null, "Year": 1483228800000, "Type": "Brazilian Naturals"}, {"Code": "THA", "Value": null, "Year": 1483228800000, "Type": "Brazilian Naturals"}, {"Code": "VNM", "Value": null, "Year": 1483228800000, "Type": "Brazilian Naturals"}, {"Code": "AGO", "Value": 120.5216, "Year": 1514764800000, "Type": "Brazilian Naturals"}, {"Code": "BRA", "Value": 90.7803, "Year": 1514764800000, "Type": "Brazilian Naturals"}, {"Code": "ETH", "Value": 70.6786, "Year": 1514764800000, "Type": "Brazilian Naturals"}, {"Code": "IDN", "Value": null, "Year": 1514764800000, "Type": "Brazilian Naturals"}, {"Code": "PHL", "Value": null, "Year": 1514764800000, "Type": "Brazilian Naturals"}, {"Code": "THA", "Value": null, "Year": 1514764800000, "Type": "Brazilian Naturals"}, {"Code": "VNM", "Value": null, "Year": 1514764800000, "Type": "Brazilian Naturals"}]