{"1009843200000":{"Antioquia":127.99232,"Bolivar":null,"Boyaca":11.3563666667,"Caldas":88.82411,"Caqueta":null,"Casanare":null,"Cauca":65.68116,"Cesar":22.43447,"Choco":null,"Cundinamarca":55.4449888889,"Guajira":4.56954,"Huila":78.23214,"Magdalena":17.45094,"Meta":null,"Nari\u00f1o":22.99809,"Norte De Santander":32.0538,"Putumayo":null,"Quindio":44.52375,"Risaralda":59.38344,"Santander":42.09321,"Tolima":105.5572277778,"Valle":86.5461444444},"1041379200000":{"Antioquia":128.05137,"Bolivar":null,"Boyaca":11.22532,"Caldas":88.50692,"Caqueta":null,"Casanare":null,"Cauca":68.4958,"Cesar":22.1868125,"Choco":null,"Cundinamarca":54.3097066667,"Guajira":4.71556,"Huila":82.19845,"Magdalena":17.5831,"Meta":null,"Nari\u00f1o":24.47217,"Norte De Santander":32.07522,"Putumayo":null,"Quindio":44.71406,"Risaralda":58.55067,"Santander":42.36052,"Tolima":105.4424133333,"Valle":85.9414733333},"1072915200000":{"Antioquia":129.29615,"Bolivar":null,"Boyaca":11.0942733333,"Caldas":90.8721,"Caqueta":null,"Casanare":null,"Cauca":69.85193,"Cesar":21.838635,"Choco":null,"Cundinamarca":53.1744244444,"Guajira":4.85043,"Huila":93.91407,"Magdalena":17.72632,"Meta":null,"Nari\u00f1o":26.14606,"Norte De Santander":32.09664,"Putumayo":null,"Quindio":44.59291,"Risaralda":57.77603,"Santander":42.75115,"Tolima":105.3275988889,"Valle":85.3368022222},"1104537600000":{"Antioquia":129.81633,"Bolivar":null,"Boyaca":10.9632266667,"Caldas":89.52036,"Caqueta":null,"Casanare":null,"Cauca":68.92067,"Cesar":21.4904575,"Choco":null,"Cundinamarca":52.0391422222,"Guajira":5.02362,"Huila":95.9206,"Magdalena":18.03557,"Meta":null,"Nari\u00f1o":26.45377,"Norte De Santander":32.11806,"Putumayo":null,"Quindio":42.95253,"Risaralda":56.854,"Santander":43.27789,"Tolima":105.2127844444,"Valle":84.7321311111},"1136073600000":{"Antioquia":126.3,"Bolivar":null,"Boyaca":10.8,"Caldas":89.1,"Caqueta":null,"Casanare":null,"Cauca":68.0,"Cesar":21.1,"Choco":null,"Cundinamarca":50.9,"Guajira":4.4,"Huila":95.1,"Magdalena":18.3,"Meta":null,"Nari\u00f1o":26.8,"Norte De Santander":32.1,"Putumayo":null,"Quindio":44.0,"Risaralda":56.2,"Santander":41.2,"Tolima":105.1,"Valle":84.1},"1167609600000":{"Antioquia":126.9,"Bolivar":null,"Boyaca":11.1,"Caldas":87.7,"Caqueta":2.8,"Casanare":2.6,"Cauca":67.8,"Cesar":21.5,"Choco":0.18,"Cundinamarca":48.2,"Guajira":5.067,"Huila":98.1,"Magdalena":17.1,"Meta":2.4,"Nari\u00f1o":27.4,"Norte De Santander":32.1,"Putumayo":null,"Quindio":43.3,"Risaralda":55.4,"Santander":41.1,"Tolima":104.3,"Valle":82.5},"1199145600000":{"Antioquia":129.1,"Bolivar":null,"Boyaca":10.7,"Caldas":85.0,"Caqueta":2.8,"Casanare":2.6,"Cauca":69.8,"Cesar":21.9,"Choco":0.189,"Cundinamarca":48.895,"Guajira":5.083,"Huila":102.5,"Magdalena":17.6,"Meta":2.4,"Nari\u00f1o":29.0,"Norte De Santander":32.6,"Putumayo":null,"Quindio":42.4,"Risaralda":54.4,"Santander":41.5,"Tolima":102.8,"Valle":77.5},"1230768000000":{"Antioquia":130.57362,"Bolivar":null,"Boyaca":10.95079,"Caldas":83.87679,"Caqueta":2.77771,"Casanare":2.558,"Cauca":73.33776,"Cesar":22.45428,"Choco":0.20017,"Cundinamarca":48.91887,"Guajira":5.18423,"Huila":104.98721,"Magdalena":18.45066,"Meta":2.2881,"Nari\u00f1o":30.99944,"Norte De Santander":33.62649,"Putumayo":null,"Quindio":39.77875,"Risaralda":54.27076,"Santander":42.74596,"Tolima":103.90545,"Valle":75.77613},"1262304000000":{"Antioquia":131.1233,"Bolivar":null,"Boyaca":11.14105,"Caldas":81.91808,"Caqueta":2.84768,"Casanare":2.60526,"Cauca":76.18941,"Cesar":24.2262,"Choco":0.18983,"Cundinamarca":49.35778,"Guajira":5.28148,"Huila":117.84218,"Magdalena":18.87203,"Meta":2.58504,"Nari\u00f1o":33.53623,"Norte De Santander":33.97512,"Putumayo":null,"Quindio":43.37053,"Risaralda":52.88379,"Santander":44.5829,"Tolima":106.79234,"Valle":75.09255},"1293840000000":{"Antioquia":131.16695,"Bolivar":null,"Boyaca":11.27251,"Caldas":80.52475,"Caqueta":3.43321,"Casanare":2.73676,"Cauca":81.17013,"Cesar":26.18866,"Choco":0.20975,"Cundinamarca":43.85455,"Guajira":5.79165,"Huila":129.15253,"Magdalena":19.76342,"Meta":3.00725,"Nari\u00f1o":35.37239,"Norte De Santander":32.90354,"Putumayo":null,"Quindio":31.07403,"Risaralda":52.56401,"Santander":45.22549,"Tolima":109.8569,"Valle":75.8},"1325376000000":{"Antioquia":133.6134,"Bolivar":null,"Boyaca":10.35444,"Caldas":78.57658,"Caqueta":3.68109,"Casanare":2.9194,"Cauca":84.06153,"Cesar":28.68801,"Choco":0.16745,"Cundinamarca":40.79406,"Guajira":6.21406,"Huila":139.13878,"Magdalena":20.55637,"Meta":3.23397,"Nari\u00f1o":37.12013,"Norte De Santander":30.01381,"Putumayo":null,"Quindio":30.18137,"Risaralda":52.31835,"Santander":46.82967,"Tolima":113.15227,"Valle":69.44382},"1356998400000":{"Antioquia":137.12591,"Bolivar":0.99843,"Boyaca":11.48672,"Caldas":77.55945,"Caqueta":4.08449,"Casanare":3.19756,"Cauca":91.60854,"Cesar":30.77295,"Choco":0.16507,"Cundinamarca":41.99428,"Guajira":6.77371,"Huila":154.49225,"Magdalena":21.2632,"Meta":3.60335,"Nari\u00f1o":39.29252,"Norte De Santander":30.39418,"Putumayo":0.04479,"Quindio":28.87981,"Risaralda":52.2728,"Santander":50.2746,"Tolima":119.33305,"Valle":68.39366},"1388534400000":{"Antioquia":130.9944,"Bolivar":1.11661,"Boyaca":11.40843,"Caldas":74.52824,"Caqueta":3.98915,"Casanare":3.25252,"Cauca":88.82609,"Cesar":30.28175,"Choco":0.1606,"Cundinamarca":37.99632,"Guajira":6.78985,"Huila":154.98293,"Magdalena":21.27153,"Meta":3.43948,"Nari\u00f1o":38.86153,"Norte De Santander":26.72628,"Putumayo":0.12865,"Quindio":27.6735,"Risaralda":51.03241,"Santander":50.3205,"Tolima":117.17887,"Valle":67.57347},"1420070400000":{"Antioquia":128.62959,"Bolivar":1.15858,"Boyaca":11.52441,"Caldas":72.36568,"Caqueta":4.09174,"Casanare":3.2001,"Cauca":92.62337,"Cesar":28.91111,"Choco":0.16336,"Cundinamarca":37.91638,"Guajira":6.12078,"Huila":154.08786,"Magdalena":20.39184,"Meta":3.53432,"Nari\u00f1o":38.84895,"Norte De Santander":25.43891,"Putumayo":0.12865,"Quindio":27.02359,"Risaralda":50.79982,"Santander":51.13646,"Tolima":118.43105,"Valle":64.39295},"1451606400000":{"Antioquia":126.3959,"Bolivar":1.18293,"Boyaca":11.44544,"Caldas":70.78863,"Caqueta":4.1559,"Casanare":3.17087,"Cauca":95.75341,"Cesar":29.01921,"Choco":0.16359,"Cundinamarca":37.67983,"Guajira":6.13069,"Huila":151.86561,"Magdalena":20.51681,"Meta":3.611,"Nari\u00f1o":38.75126,"Norte De Santander":24.33636,"Putumayo":0.0,"Quindio":25.68484,"Risaralda":50.25564,"Santander":50.60888,"Tolima":117.27424,"Valle":62.95528},"1483228800000":{"Antioquia":123.25658,"Bolivar":1.23128,"Boyaca":10.56771,"Caldas":68.96862,"Caqueta":4.05336,"Casanare":2.9163,"Cauca":93.30242,"Cesar":28.03272,"Choco":0.17037,"Cundinamarca":35.42518,"Guajira":5.86201,"Huila":147.80466,"Magdalena":20.16975,"Meta":3.40091,"Nari\u00f1o":38.16973,"Norte De Santander":23.9855,"Putumayo":0.22464,"Quindio":23.75508,"Risaralda":48.51667,"Santander":50.15844,"Tolima":112.86673,"Valle":61.11278},"1514764800000":{"Antioquia":120.96247,"Bolivar":1.31422,"Boyaca":10.41157,"Caldas":66.01964,"Caqueta":4.02463,"Casanare":2.73515,"Cauca":92.56067,"Cesar":25.95149,"Choco":0.17086,"Cundinamarca":32.32467,"Guajira":5.14048,"Huila":146.7627,"Magdalena":19.39406,"Meta":2.89572,"Nari\u00f1o":37.26383,"Norte De Santander":23.5565,"Putumayo":0.22634,"Quindio":21.25027,"Risaralda":46.39416,"Santander":50.65962,"Tolima":111.71078,"Valle":55.41395},"1546300800000":{"Antioquia":119.15522,"Bolivar":1.38602,"Boyaca":10.25207,"Caldas":63.05112,"Caqueta":3.99292,"Casanare":2.60431,"Cauca":92.67453,"Cesar":23.62906,"Choco":0.17656,"Cundinamarca":30.3076,"Guajira":4.25415,"Huila":144.89587,"Magdalena":17.95868,"Meta":2.88647,"Nari\u00f1o":36.15937,"Norte De Santander":23.02689,"Putumayo":0.21378,"Quindio":20.0228,"Risaralda":45.12692,"Santander":51.34622,"Tolima":108.16579,"Valle":52.41174}}